{
	"name": "FishBag",
	"plugin-id": "Sprite",
	"sid": 245445590396917,
	"isGlobal": false,
	"editorNewInstanceIsReplica": true,
	"instanceVariables": [],
	"behaviorTypes": [],
	"effectTypes": [],
	"animations": {
		"items": [
			{
				"frames": [
					{
						"width": 64,
						"height": 64,
						"originX": 0.5,
						"originY": 0.5,
						"originalSource": "",
						"exportFormat": "lossless",
						"exportQuality": 0.8,
						"fileType": "image/png",
						"imageSpriteId": 5388785,
						"collisionPoly": {
							"points": [
								0.5,
								0.375,
								0.546875,
								0.375,
								0.640625,
								0.515625,
								0.640625,
								0.5625,
								0.5625,
								0.625,
								0.4375,
								0.625,
								0.390625,
								0.578125,
								0.390625,
								0.5,
								0.421875,
								0.390625
							]
						},
						"useCollisionPoly": true,
						"duration": 1,
						"tag": ""
					}
				],
				"sid": 709046021523040,
				"name": "0",
				"isLooping": false,
				"isPingPong": false,
				"repeatCount": 1,
				"repeatTo": 0,
				"speed": 5
			},
			{
				"frames": [
					{
						"width": 64,
						"height": 64,
						"originX": 0.5,
						"originY": 0.5,
						"originalSource": "",
						"exportFormat": "lossless",
						"exportQuality": 0.8,
						"fileType": "image/png",
						"imageSpriteId": 4582574,
						"collisionPoly": {
							"points": [
								0.5,
								0.375,
								0.546875,
								0.375,
								0.640625,
								0.515625,
								0.640625,
								0.5625,
								0.5625,
								0.625,
								0.4375,
								0.625,
								0.390625,
								0.578125,
								0.390625,
								0.5,
								0.421875,
								0.390625
							]
						},
						"useCollisionPoly": true,
						"duration": 1,
						"tag": ""
					}
				],
				"sid": 604256543919139,
				"name": "1",
				"isLooping": false,
				"isPingPong": false,
				"repeatCount": 1,
				"repeatTo": 0,
				"speed": 5
			},
			{
				"frames": [
					{
						"width": 64,
						"height": 64,
						"originX": 0.5,
						"originY": 0.5,
						"originalSource": "",
						"exportFormat": "lossless",
						"exportQuality": 0.8,
						"fileType": "image/png",
						"imageSpriteId": 8899950,
						"collisionPoly": {
							"points": [
								0.4375,
								0.34375,
								0.546875,
								0.34375,
								0.59375,
								0.359375,
								0.640625,
								0.515625,
								0.640625,
								0.5625,
								0.625,
								0.625,
								0.578125,
								0.671875,
								0.4375,
								0.671875,
								0.359375,
								0.609375,
								0.359375,
								0.546875,
								0.390625,
								0.375
							]
						},
						"useCollisionPoly": true,
						"duration": 1,
						"tag": ""
					}
				],
				"sid": 490948698576727,
				"name": "2",
				"isLooping": false,
				"isPingPong": false,
				"repeatCount": 1,
				"repeatTo": 0,
				"speed": 5
			},
			{
				"frames": [
					{
						"width": 64,
						"height": 64,
						"originX": 0.5,
						"originY": 0.5,
						"originalSource": "",
						"exportFormat": "lossless",
						"exportQuality": 0.8,
						"fileType": "image/png",
						"imageSpriteId": 2249881,
						"collisionPoly": {
							"points": [
								0.4375,
								0.359375,
								0.515625,
								0.359375,
								0.578125,
								0.375,
								0.640625,
								0.515625,
								0.625,
								0.6875,
								0.578125,
								0.703125,
								0.375,
								0.6875,
								0.359375,
								0.609375,
								0.359375,
								0.546875,
								0.390625,
								0.390625
							]
						},
						"useCollisionPoly": true,
						"duration": 1,
						"tag": ""
					}
				],
				"sid": 762932281507464,
				"name": "3",
				"isLooping": false,
				"isPingPong": false,
				"repeatCount": 1,
				"repeatTo": 0,
				"speed": 5
			},
			{
				"frames": [
					{
						"width": 64,
						"height": 64,
						"originX": 0.5,
						"originY": 0.5,
						"originalSource": "",
						"exportFormat": "lossless",
						"exportQuality": 0.8,
						"fileType": "image/png",
						"imageSpriteId": 2395407,
						"collisionPoly": {
							"points": [
								0.4375,
								0.359375,
								0.515625,
								0.359375,
								0.578125,
								0.375,
								0.671875,
								0.53125,
								0.65625,
								0.703125,
								0.578125,
								0.75,
								0.421875,
								0.75,
								0.3125,
								0.671875,
								0.3125,
								0.578125,
								0.390625,
								0.390625
							]
						},
						"useCollisionPoly": true,
						"duration": 1,
						"tag": ""
					}
				],
				"sid": 558670391510053,
				"name": "4",
				"isLooping": false,
				"isPingPong": false,
				"repeatCount": 1,
				"repeatTo": 0,
				"speed": 5
			},
			{
				"frames": [
					{
						"width": 64,
						"height": 64,
						"originX": 0.5,
						"originY": 0.5,
						"originalSource": "",
						"exportFormat": "lossless",
						"exportQuality": 0.8,
						"fileType": "image/png",
						"imageSpriteId": 4832844,
						"collisionPoly": {
							"points": [
								0.4375,
								0.359375,
								0.515625,
								0.359375,
								0.578125,
								0.375,
								0.703125,
								0.5625,
								0.703125,
								0.65625,
								0.671875,
								0.734375,
								0.625,
								0.78125,
								0.375,
								0.78125,
								0.296875,
								0.703125,
								0.296875,
								0.609375,
								0.390625,
								0.390625
							]
						},
						"useCollisionPoly": true,
						"duration": 1,
						"tag": ""
					}
				],
				"sid": 383411035982810,
				"name": "5",
				"isLooping": false,
				"isPingPong": false,
				"repeatCount": 1,
				"repeatTo": 0,
				"speed": 5
			},
			{
				"frames": [
					{
						"width": 64,
						"height": 64,
						"originX": 0.5,
						"originY": 0.5,
						"originalSource": "",
						"exportFormat": "lossless",
						"exportQuality": 0.8,
						"fileType": "image/png",
						"imageSpriteId": 8055243,
						"collisionPoly": {
							"points": [
								0.4375,
								0.359375,
								0.515625,
								0.359375,
								0.578125,
								0.375,
								0.703125,
								0.546875,
								0.703125,
								0.6875,
								0.6875,
								0.734375,
								0.640625,
								0.796875,
								0.578125,
								0.84375,
								0.515625,
								0.859375,
								0.46875,
								0.859375,
								0.390625,
								0.84375,
								0.328125,
								0.78125,
								0.296875,
								0.734375,
								0.3125,
								0.515625,
								0.390625,
								0.390625
							]
						},
						"useCollisionPoly": true,
						"duration": 1,
						"tag": ""
					}
				],
				"sid": 489872327495677,
				"name": "6",
				"isLooping": false,
				"isPingPong": false,
				"repeatCount": 1,
				"repeatTo": 0,
				"speed": 5
			},
			{
				"frames": [
					{
						"width": 64,
						"height": 64,
						"originX": 0.5,
						"originY": 0.5,
						"originalSource": "",
						"exportFormat": "lossless",
						"exportQuality": 0.8,
						"fileType": "image/png",
						"imageSpriteId": 280137,
						"collisionPoly": {
							"points": [
								0.4375,
								0.359375,
								0.515625,
								0.359375,
								0.578125,
								0.375,
								0.703125,
								0.546875,
								0.734375,
								0.671875,
								0.734375,
								0.796875,
								0.640625,
								0.890625,
								0.59375,
								0.90625,
								0.40625,
								0.90625,
								0.359375,
								0.890625,
								0.265625,
								0.796875,
								0.25,
								0.734375,
								0.25,
								0.625,
								0.390625,
								0.390625
							]
						},
						"useCollisionPoly": true,
						"duration": 1,
						"tag": ""
					}
				],
				"sid": 400317440680647,
				"name": "7",
				"isLooping": false,
				"isPingPong": false,
				"repeatCount": 1,
				"repeatTo": 0,
				"speed": 5
			},
			{
				"frames": [
					{
						"width": 64,
						"height": 64,
						"originX": 0.5,
						"originY": 0.5,
						"originalSource": "",
						"exportFormat": "lossless",
						"exportQuality": 0.8,
						"fileType": "image/png",
						"imageSpriteId": 8106298,
						"collisionPoly": {
							"points": [
								0.4375,
								0.265625,
								0.515625,
								0.265625,
								0.578125,
								0.28125,
								0.71875,
								0.4375,
								0.765625,
								0.515625,
								0.78125,
								0.578125,
								0.765625,
								0.765625,
								0.71875,
								0.828125,
								0.671875,
								0.859375,
								0.609375,
								0.875,
								0.328125,
								0.859375,
								0.21875,
								0.75,
								0.21875,
								0.5625,
								0.28125,
								0.421875,
								0.390625,
								0.296875
							]
						},
						"useCollisionPoly": true,
						"duration": 1,
						"tag": ""
					}
				],
				"sid": 717622872339607,
				"name": "8",
				"isLooping": false,
				"isPingPong": false,
				"repeatCount": 1,
				"repeatTo": 0,
				"speed": 5
			},
			{
				"frames": [
					{
						"width": 64,
						"height": 64,
						"originX": 0.5,
						"originY": 0.5,
						"originalSource": "",
						"exportFormat": "lossless",
						"exportQuality": 0.8,
						"fileType": "image/png",
						"imageSpriteId": 8406455,
						"collisionPoly": {
							"points": [
								0.4375,
								0.265625,
								0.515625,
								0.265625,
								0.578125,
								0.28125,
								0.71875,
								0.4375,
								0.84375,
								0.640625,
								0.875,
								0.703125,
								0.875,
								0.796875,
								0.828125,
								0.859375,
								0.671875,
								0.90625,
								0.390625,
								0.90625,
								0.3125,
								0.890625,
								0.15625,
								0.828125,
								0.09375,
								0.765625,
								0.109375,
								0.671875,
								0.28125,
								0.421875,
								0.390625,
								0.296875
							]
						},
						"useCollisionPoly": true,
						"duration": 1,
						"tag": ""
					}
				],
				"sid": 242669551882045,
				"name": "9",
				"isLooping": false,
				"isPingPong": false,
				"repeatCount": 1,
				"repeatTo": 0,
				"speed": 5
			},
			{
				"frames": [
					{
						"width": 64,
						"height": 64,
						"originX": 0.5,
						"originY": 0.5,
						"originalSource": "",
						"exportFormat": "lossless",
						"exportQuality": 0.8,
						"fileType": "image/png",
						"imageSpriteId": 6257203,
						"collisionPoly": {
							"points": [
								0.4375,
								0.25,
								0.53125,
								0.25,
								0.65625,
								0.296875,
								0.890625,
								0.65625,
								0.90625,
								0.734375,
								0.90625,
								0.859375,
								0.859375,
								0.90625,
								0.640625,
								0.953125,
								0.4375,
								0.953125,
								0.203125,
								0.921875,
								0.15625,
								0.90625,
								0.09375,
								0.84375,
								0.09375,
								0.703125,
								0.1875,
								0.515625
							]
						},
						"useCollisionPoly": true,
						"duration": 1,
						"tag": ""
					}
				],
				"sid": 794399268586431,
				"name": "10",
				"isLooping": false,
				"isPingPong": false,
				"repeatCount": 1,
				"repeatTo": 0,
				"speed": 5
			}
		],
		"subfolders": []
	}
}