{
	"name": "Main Event Sheet",
	"events": [
		{
			"eventType": "block",
			"conditions": [
				{
					"id": "on-start-of-layout",
					"objectClass": "System",
					"sid": 323257818288910
				}
			],
			"actions": [
				{
					"id": "add-object-to-target",
					"objectClass": "WatcherEye",
					"sid": 260921929371809,
					"behaviorType": "Turret",
					"parameters": {
						"target": "Cat"
					}
				},
				{
					"id": "add-object-to-target",
					"objectClass": "TurretEye",
					"sid": 246806483193239,
					"behaviorType": "Turret",
					"parameters": {
						"target": "Cat"
					}
				}
			],
			"sid": 567072861494963
		},
		{
			"eventType": "block",
			"conditions": [
				{
					"id": "on-shoot",
					"objectClass": "TurretEye",
					"sid": 180453060112399,
					"behaviorType": "Turret"
				}
			],
			"actions": [
				{
					"id": "spawn-another-object",
					"objectClass": "TurretEye",
					"sid": 237455577353356,
					"parameters": {
						"object": "Bullet",
						"layer": "0",
						"image-point": "1",
						"create-hierarchy": false,
						"template-name": "\"\""
					}
				}
			],
			"sid": 392899114026205
		},
		{
			"eventType": "block",
			"conditions": [
				{
					"id": "on-timer",
					"objectClass": "Bullet",
					"sid": 812263440610967,
					"behaviorType": "Timer",
					"parameters": {
						"tag": "\"Expire\""
					}
				}
			],
			"actions": [
				{
					"id": "destroy",
					"objectClass": "Bullet",
					"sid": 158653742524930
				}
			],
			"sid": 928167487866288
		},
		{
			"eventType": "block",
			"conditions": [
				{
					"id": "on-created",
					"objectClass": "Bullet",
					"sid": 165028049645473
				}
			],
			"actions": [
				{
					"id": "start-timer",
					"objectClass": "Bullet",
					"sid": 480666156228685,
					"behaviorType": "Timer",
					"parameters": {
						"duration": "2",
						"type": "once",
						"tag": "\"Expire\""
					}
				}
			],
			"sid": 488175565636147
		},
		{
			"eventType": "block",
			"conditions": [
				{
					"id": "on-start-of-layout",
					"objectClass": "System",
					"sid": 221670024867708
				}
			],
			"actions": [
				{
					"callFunction": "IntroTransistion",
					"sid": 904909839364625
				}
			],
			"sid": 591116348898262
		}
	],
	"sid": 674151678432048
}